setup.cfg
setup.py
pyf/__init__.py
pyf.components.adapters.reordering.egg-info/PKG-INFO
pyf.components.adapters.reordering.egg-info/SOURCES.txt
pyf.components.adapters.reordering.egg-info/dependency_links.txt
pyf.components.adapters.reordering.egg-info/entry_points.txt
pyf.components.adapters.reordering.egg-info/namespace_packages.txt
pyf.components.adapters.reordering.egg-info/requires.txt
pyf.components.adapters.reordering.egg-info/top_level.txt
pyf.components.adapters.reordering.egg-info/zip-safe
pyf/components/__init__.py
pyf/components/adapters/__init__.py
pyf/components/adapters/reordering/__init__.py
pyf/components/adapters/reordering/reordering.py
pyf/components/adapters/reordering/tests/__init__.py
pyf/components/adapters/reordering/tests/test_reordering.py