Metadata-Version: 1.0
Name: pyf.components.adapters.reordering
Version: 1.0
Summary: PyF Flow on-disk reordering adapters (for serializable objects)
Home-page: http://www.pyfproject.org/
Author: Jonathan Schemoul
Author-email: jonathan.schemoul@gmail.com
License: MIT or PSF
Platform: UNKNOWN
Classifier: Development Status :: 3 - Alpha
Classifier: Operating System :: OS Independent
Classifier: Programming Language :: Python
Classifier: License :: OSI Approved :: MIT License
Classifier: Topic :: Software Development :: Libraries :: Python Modules
